linkbar/__init__.py
linkbar/domain.py
linkbar/link.py
tests/__init__.py
tests/test_client.py
tests/test_domain.py
tests/test_integration.py
tests/test_link.py
linkbar-1.0.0.dist-info/METADATA
linkbar-1.0.0.dist-info/WHEEL
linkbar-1.0.0.dist-info/top_level.txt
linkbar-1.0.0.dist-info/RECORD
